.coveragerc
.testr.conf
AUTHORS
CONTRIBUTING.rst
ChangeLog
HACKING.rst
LICENSE
MANIFEST.in
README.rst
babel.cfg
install.sh
openstack-common.conf
pylintrc
requirements.txt
run_tests.sh
setup.cfg
setup.py
test-requirements.txt
tox.ini
uninstall.sh
bin/cinder-keystone-setup
bin/heat-api
bin/heat-api-cfn
bin/heat-api-cloudwatch
bin/heat-db-setup
bin/heat-engine
bin/heat-keystone-setup
bin/heat-keystone-setup-domain
bin/heat-manage
contrib/extraroute/README.md
contrib/extraroute/setup.cfg
contrib/extraroute/setup.py
contrib/extraroute/extraroute/__init__.py
contrib/extraroute/extraroute/resources/__init__.py
contrib/extraroute/extraroute/resources/extraroute.py
contrib/extraroute/extraroute/tests/__init__.py
contrib/extraroute/extraroute/tests/test_extraroute.py
contrib/heat_barbican/README.md
contrib/heat_barbican/requirements.txt
contrib/heat_barbican/setup.cfg
contrib/heat_barbican/setup.py
contrib/heat_barbican/heat_barbican/__init__.py
contrib/heat_barbican/heat_barbican/client.py
contrib/heat_barbican/heat_barbican/resources/__init__.py
contrib/heat_barbican/heat_barbican/resources/order.py
contrib/heat_barbican/heat_barbican/resources/secret.py
contrib/heat_barbican/heat_barbican/tests/__init__.py
contrib/heat_barbican/heat_barbican/tests/test_order.py
contrib/heat_barbican/heat_barbican/tests/test_secret.py
contrib/heat_docker/README.md
contrib/heat_docker/requirements.txt
contrib/heat_docker/setup.cfg
contrib/heat_docker/setup.py
contrib/heat_docker/heat_docker/__init__.py
contrib/heat_docker/heat_docker/resources/__init__.py
contrib/heat_docker/heat_docker/resources/docker_container.py
contrib/heat_docker/heat_docker/tests/__init__.py
contrib/heat_docker/heat_docker/tests/fake_docker_client.py
contrib/heat_docker/heat_docker/tests/test_docker_container.py
contrib/heat_keystoneclient_v2/README.md
contrib/heat_keystoneclient_v2/setup.cfg
contrib/heat_keystoneclient_v2/setup.py
contrib/heat_keystoneclient_v2/heat_keystoneclient_v2/__init__.py
gbptestheat.egg-info/PKG-INFO
gbptestheat.egg-info/SOURCES.txt
gbptestheat.egg-info/dependency_links.txt
gbptestheat.egg-info/entry_points.txt
gbptestheat.egg-info/not-zip-safe
gbptestheat.egg-info/requires.txt
gbptestheat.egg-info/top_level.txt
